{
    "applicationID": "5",
    "applicationName": "Piezometer",
    "deviceName": "802",
    "devEUI": "BykzFAUtLvA=",
    "rxInfo": [
        {
            "gatewayID": "eF7o//4gAPE=",
            "time": null,
            "timeSinceGPSEpoch": null,
            "rssi": -106,
            "loRaSNR": 6,
            "channel": 4,
            "rfChain": 0,
            "board": 0,
            "antenna": 0,
            "location": {
                "latitude": 0,
                "longitude": 0,
                "altitude": 0,
                "source": "UNKNOWN",
                "accuracy": 0
            },
            "fineTimestampType": "NONE",
            "context": "1r6M7A==",
            "uplinkID": "cDPxiI5uR5egVdu6rtoRpQ==",
            "crcStatus": "CRC_OK"
        }
    ],
    "txInfo": {
        "frequency": 864900000,
        "modulation": "LORA",
        "loRaModulationInfo": {
            "bandwidth": 125,
            "spreadingFactor": 12,
            "codeRate": "4/5",
            "polarizationInversion": false
        }
    },
    "adr": false,
    "dr": 0,
    "fCnt": 14,
    "fPort": 60,
    "data": "G2MyLsgAAASZAABK6g==",
    "objectJSON": "",
    "tags": {},
    "confirmedUplink": true,
    "devAddr": "AOE7UQ==",
    "publishedAt": "2022-09-26T23:03:10.774413456Z"
}